wagtail_vector_index/__init__.py
wagtail_vector_index/ai.py
wagtail_vector_index/apps.py
wagtail_vector_index/models.py
wagtail_vector_index/ai_utils/__init__.py
wagtail_vector_index/ai_utils/embeddings.py
wagtail_vector_index/ai_utils/tokens.py
wagtail_vector_index/ai_utils/types.py
wagtail_vector_index/ai_utils/backends/__init__.py
wagtail_vector_index/ai_utils/backends/base.py
wagtail_vector_index/ai_utils/backends/echo.py
wagtail_vector_index/ai_utils/backends/litellm.py
wagtail_vector_index/ai_utils/backends/llm.py
wagtail_vector_index/ai_utils/text_splitting/__init__.py
wagtail_vector_index/ai_utils/text_splitting/dummy.py
wagtail_vector_index/ai_utils/text_splitting/langchain.py
wagtail_vector_index/ai_utils/text_splitting/naive.py
wagtail_vector_index/management/__init__.py
wagtail_vector_index/management/commands/__init__.py
wagtail_vector_index/management/commands/update_vector_indexes.py
wagtail_vector_index/migrations/0001_initial.py
wagtail_vector_index/migrations/__init__.py
wagtail_vector_index/storage/__init__.py
wagtail_vector_index/storage/base.py
wagtail_vector_index/storage/exceptions.py
wagtail_vector_index/storage/models.py
wagtail_vector_index/storage/registry.py
wagtail_vector_index/storage/numpy/__init__.py
wagtail_vector_index/storage/numpy/provider.py
wagtail_vector_index/storage/pgvector/__init__.py
wagtail_vector_index/storage/pgvector/apps.py
wagtail_vector_index/storage/pgvector/models.py
wagtail_vector_index/storage/pgvector/provider.py
wagtail_vector_index/storage/pgvector/types.py
wagtail_vector_index/storage/pgvector/migrations/0001_enable_pgvector_extension.py
wagtail_vector_index/storage/pgvector/migrations/0002_initial.py
wagtail_vector_index/storage/pgvector/migrations/__init__.py
wagtail_vector_index/storage/qdrant/__init__.py
wagtail_vector_index/storage/qdrant/provider.py
wagtail_vector_index/storage/weaviate/__init__.py
wagtail_vector_index/storage/weaviate/provider.py
wagtail_vector_index-0.10.0.dist-info/LICENSE
wagtail_vector_index-0.10.0.dist-info/LICENSE_LANGCHAIN
wagtail_vector_index-0.10.0.dist-info/WHEEL
wagtail_vector_index-0.10.0.dist-info/METADATA
wagtail_vector_index-0.10.0.dist-info/RECORD
