Metadata-Version: 2.1
Name: wagtail-vector-index
Version: 0.10.0
Summary: Add your content to vector indexes for fast search and similarity matching.
Author-email: Tom Usher <tom@tomusher.com>
Requires-Python: >=3.11
Classifier: Development Status :: 3 - Alpha
Classifier: Intended Audience :: Developers
Classifier: License :: OSI Approved :: MIT License
Classifier: Operating System :: OS Independent
Classifier: Programming Language :: Python
Classifier: Programming Language :: Python :: 3
Classifier: Programming Language :: Python :: 3.11
Classifier: Programming Language :: Python :: 3.12
Classifier: Framework :: Django
Classifier: Framework :: Django :: 4.2
Classifier: Framework :: Wagtail
Classifier: Framework :: Wagtail :: 5
Requires-Dist: Django>=4.2
Requires-Dist: Wagtail>=5.2
Requires-Dist: litellm>=1.40.15,<1.40.16
Requires-Dist: openai>=1.28.1
Requires-Dist: aiohttp>=3.9.0b0; python_version >= '3.12'
Requires-Dist: mkdocs>=1.5.3 ; extra == "docs"
Requires-Dist: mkdocs-material>=9.4.5 ; extra == "docs"
Requires-Dist: mkdocs-awesome-pages-plugin>=2.9.2 ; extra == "docs"
Requires-Dist: llm>=0.12 ; extra == "llm"
Requires-Dist: numpy>=1.26.0 ; extra == "numpy"
Requires-Dist: pgvector>=0.2.3 ; extra == "pgvector"
Requires-Dist: qdrant-client>=1.6.0 ; extra == "qdrant"
Requires-Dist: dj-database-url==2.1.0 ; extra == "testing"
Requires-Dist: pre-commit>=3.4.0 ; extra == "testing"
Requires-Dist: pytest>=7.4.2 ; extra == "testing"
Requires-Dist: pytest-asyncio>=0.23.6 ; extra == "testing"
Requires-Dist: pytest-mock>=3.12.0 ; extra == "testing"
Requires-Dist: pytest-django>=4.5.2 ; extra == "testing"
Requires-Dist: wagtail-factories>=4.1.0 ; extra == "testing"
Requires-Dist: factory-boy>=3.3.0 ; extra == "testing"
Requires-Dist: coverage>=7.0,<8.0 ; extra == "testing"
Requires-Dist: pyright>=1.1.366 ; extra == "testing"
Requires-Dist: django-types>=0.19.1 ; extra == "testing"
Requires-Dist: weaviate-client>=3.24.2 ; extra == "weaviate"
Project-URL: Home, https://github.com/wagtail/wagtail-vector-index
Provides-Extra: docs
Provides-Extra: llm
Provides-Extra: numpy
Provides-Extra: pgvector
Provides-Extra: qdrant
Provides-Extra: testing
Provides-Extra: weaviate
